{
  "objectInfo" : {
    "id" : "bZbMhiS4Fael0q1NIbWGaQ",
    "name" : "Empty_Project_Renamed",
    "type" : "Project",
    "metadata" : {
      "modelVersion" : {
        "major" : 0,
        "minor" : 0
      },
      "repoInfo" : null,
      "contextAttributes" : [ ],
      "additionalInfo" : {
        "description" : "Project To be Renamed",
        "contentType" : "Binary",
        "documentState" : "COMPLETE"
      }
    }
  },
  "dataFileExtension" : "json",
  "updateTime" : "2023-08-24T06:25:41.842Z",
  "objectRefs" : [ ]
}